codegen_api_client/api_response.py
codegen_api_client/exceptions.py
codegen_api_client/models/http_validation_error.py
codegen_api_client/models/validation_error_loc_inner.py
codegen_api_client/models/organization_settings.py
codegen_api_client/models/validation_error.py
codegen_api_client/models/fast_api_rate_limit_response.py
codegen_api_client/models/organization_response.py
codegen_api_client/models/page_user_response.py
codegen_api_client/models/create_agent_run_input.py
codegen_api_client/models/page_organization_response.py
codegen_api_client/models/__init__.py
codegen_api_client/models/user_response.py
codegen_api_client/models/agent_run_response.py
codegen_api_client/api/users_api.py
codegen_api_client/api/agents_api.py
codegen_api_client/api/organizations_api.py
codegen_api_client/api/__init__.py
codegen_api_client/py.typed
codegen_api_client/configuration.py
codegen_api_client/rest.py
codegen_api_client/api_client.py
codegen_api_client/__init__.py
codegen_api_client-1.0.0.dist-info/WHEEL
codegen_api_client-1.0.0.dist-info/METADATA
codegen_api_client-1.0.0.dist-info/RECORD
