Metadata-Version: 2.4
Name: codegen-api-client
Version: 1.0.0
Summary: Developer API
Keywords: OpenAPI,OpenAPI-Generator,Developer API
Author: OpenAPI Generator Community
Author-email: OpenAPI Generator Community <team@openapitools.org>
License-Expression: Apache-2.0
Requires-Dist: urllib3>=1.25.3,<3.0.0
Requires-Dist: python-dateutil>=2.8.2
Requires-Dist: pydantic>=2
Requires-Dist: typing-extensions>=4.7.1
Requires-Python: ~=3.8
Project-URL: Repository, https://github.com/codegen-sh/codegen-api-client
